{
  "metadata": {
    "source": "/Users/adiazescobar/Downloads/plantas_cuidado_dashboard.xlsx",
    "generatedAt": "2026-05-25",
    "description": "Datos iniciales importados desde plantas_cuidado_dashboard.xlsx"
  },
  "plants": [
    {
      "id": 1,
      "slug": "monstera-adansonii",
      "commonName": "Monstera adansonii",
      "probableSpecies": "Monstera adansonii",
      "location": "Por definir",
      "zone": "normal",
      "plantType": "tropical_exigente",
      "humidifierPriority": "no",
      "currentPH": 6.9,
      "currentMoisture": 57,
      "currentLight": 777,
      "temperature": "Por medir",
      "generalState": "Estable",
      "diagnosis": "Hojas bajas amarillas; revisar riego/luz",
      "mainProblem": "Hojas bajas amarillas; revisar riego/luz",
      "urgentActions": "Retirar hojas amarillas y revisar drenaje",
      "maintenanceActions": "Mantener riego moderado y luz indirecta brillante",
      "reviewFrequency": "Semanal",
      "lastReviewDate": "2026-05-25",
      "nextRecommendedAction": "Mantener riego moderado y luz indirecta brillante",
      "notes": "pH aceptable; humedad algo alta pero tolerable",
      "initialHumidifierNote": "No obligatorio",
      "measurements": [
        {
          "date": "2026-05-25",
          "ph": 6.9,
          "moisture": 57,
          "light": 777,
          "state": "Estable",
          "note": "Medición inicial importada desde Excel"
        }
      ],
      "photos": []
    },
    {
      "id": 2,
      "slug": "anthurium-velvet-queen",
      "commonName": "Anthurium velvet / Queen",
      "probableSpecies": "Anthurium warocqueanum o híbrido velvet",
      "location": "Por definir",
      "zone": "humidificador",
      "plantType": "tropical_exigente",
      "humidifierPriority": "alta",
      "currentPH": 7.3,
      "currentMoisture": 38,
      "currentLight": 1980,
      "temperature": "Por medir",
      "generalState": "Estrés moderado",
      "diagnosis": "Bordes secos; humedad ambiental insuficiente",
      "mainProblem": "Bordes secos; humedad ambiental insuficiente",
      "urgentActions": "Agrupar en zona húmeda y poner humidificador",
      "maintenanceActions": "Agua filtrada/lluvia; mantener sustrato aireado",
      "reviewFrequency": "Semanal",
      "lastReviewDate": "2026-05-25",
      "nextRecommendedAction": "Agua filtrada/lluvia; mantener sustrato aireado",
      "notes": "Muy sensible a humedad y sales",
      "initialHumidifierNote": "SÍ, sí o sí",
      "measurements": [
        {
          "date": "2026-05-25",
          "ph": 7.3,
          "moisture": 38,
          "light": 1980,
          "state": "Estrés moderado",
          "note": "Medición inicial importada desde Excel"
        }
      ],
      "photos": []
    },
    {
      "id": 3,
      "slug": "suculenta-colgante",
      "commonName": "Suculenta colgante",
      "probableSpecies": "Peperomia rotundifolia / Callisia-like",
      "location": "Por definir",
      "zone": "seca",
      "plantType": "cactus_sansevieria",
      "humidifierPriority": "no",
      "currentPH": 7.9,
      "currentMoisture": 27,
      "currentLight": 862,
      "temperature": "Por medir",
      "generalState": "Estresada",
      "diagnosis": "Tallos desnudos; poca luz/edad/estrés hídrico",
      "mainProblem": "Tallos desnudos; poca luz/edad/estrés hídrico",
      "urgentActions": "Podar tallos secos y propagar puntas vivas",
      "maintenanceActions": "Más luz; sustrato más drenante",
      "reviewFrequency": "Semanal",
      "lastReviewDate": "2026-05-25",
      "nextRecommendedAction": "Más luz; sustrato más drenante",
      "notes": "Evitar humidificador directo",
      "initialHumidifierNote": "No",
      "measurements": [
        {
          "date": "2026-05-25",
          "ph": 7.9,
          "moisture": 27,
          "light": 862,
          "state": "Estresada",
          "note": "Medición inicial importada desde Excel"
        }
      ],
      "photos": []
    },
    {
      "id": 4,
      "slug": "alocasia-plateada",
      "commonName": "Alocasia plateada",
      "probableSpecies": "Alocasia baginda / Silver Dragon-type",
      "location": "Por definir",
      "zone": "humidificador",
      "plantType": "tropical_exigente",
      "humidifierPriority": "alta",
      "currentPH": 6.7,
      "currentMoisture": 73,
      "currentLight": 1165,
      "temperature": "Por medir",
      "generalState": "Estrés moderado",
      "diagnosis": "Exceso de humedad + bordes secos",
      "mainProblem": "Exceso de humedad + bordes secos",
      "urgentActions": "No regar hasta bajar humedad; ubicar en zona húmeda con aire",
      "maintenanceActions": "Sustrato más aireado si persiste",
      "reviewFrequency": "Semanal",
      "lastReviewDate": "2026-05-25",
      "nextRecommendedAction": "Sustrato más aireado si persiste",
      "notes": "Requiere humedad ambiental, no sustrato empapado",
      "initialHumidifierNote": "SÍ, sí o sí",
      "measurements": [
        {
          "date": "2026-05-25",
          "ph": 6.7,
          "moisture": 73,
          "light": 1165,
          "state": "Estrés moderado",
          "note": "Medición inicial importada desde Excel"
        }
      ],
      "photos": []
    },
    {
      "id": 5,
      "slug": "anthurium-oscuro-con-espatas",
      "commonName": "Anthurium oscuro con espatas",
      "probableSpecies": "Anthurium andreanum/híbrido oscuro",
      "location": "Por definir",
      "zone": "normal",
      "plantType": "tropical_exigente",
      "humidifierPriority": "media",
      "currentPH": 6.4,
      "currentMoisture": 95,
      "currentLight": 527,
      "temperature": "Por medir",
      "generalState": "Estable",
      "diagnosis": "Sustrato demasiado húmedo",
      "mainProblem": "Sustrato demasiado húmedo",
      "urgentActions": "Suspender riego y verificar drenaje",
      "maintenanceActions": "Airear sustrato",
      "reviewFrequency": "Semanal",
      "lastReviewDate": "2026-05-25",
      "nextRecommendedAction": "Airear sustrato",
      "notes": "pH bien; ojo raíces",
      "initialHumidifierNote": "Opcional",
      "measurements": [
        {
          "date": "2026-05-25",
          "ph": 6.4,
          "moisture": 95,
          "light": 527,
          "state": "Estable",
          "note": "Medición inicial importada desde Excel"
        }
      ],
      "photos": []
    },
    {
      "id": 6,
      "slug": "ficus-lyrata-1",
      "commonName": "Ficus lyrata 1",
      "probableSpecies": "Ficus lyrata",
      "location": "Por definir",
      "zone": "normal",
      "plantType": "tropical",
      "humidifierPriority": "no",
      "currentPH": 7,
      "currentMoisture": null,
      "currentLight": 3920,
      "temperature": "Por medir",
      "generalState": "Estable con estrés",
      "diagnosis": "Hojas viejas secas; sustrato compacto",
      "mainProblem": "Hojas viejas secas; sustrato compacto",
      "urgentActions": "Retirar hojas muertas; riego solo cuando seque",
      "maintenanceActions": "Mejorar drenaje en trasplante",
      "reviewFrequency": "Semanal",
      "lastReviewDate": "2026-05-25",
      "nextRecommendedAction": "Mejorar drenaje en trasplante",
      "notes": "No ubicar en humidificador",
      "initialHumidifierNote": "No",
      "measurements": [
        {
          "date": "2026-05-25",
          "ph": 7,
          "moisture": null,
          "light": 3920,
          "state": "Estable con estrés",
          "note": "Medición inicial importada desde Excel"
        }
      ],
      "photos": []
    },
    {
      "id": 7,
      "slug": "ficus-lyrata-2",
      "commonName": "Ficus lyrata 2",
      "probableSpecies": "Ficus lyrata",
      "location": "Por definir",
      "zone": "normal",
      "plantType": "tropical",
      "humidifierPriority": "no",
      "currentPH": 8.9,
      "currentMoisture": null,
      "currentLight": null,
      "temperature": "Por medir",
      "generalState": "Estrés moderado",
      "diagnosis": "pH muy alto; clorosis/manchas",
      "mainProblem": "pH muy alto; clorosis/manchas",
      "urgentActions": "Lavar sales con riego profundo si hay drenaje",
      "maintenanceActions": "Cambiar a sustrato más aireado",
      "reviewFrequency": "Semanal",
      "lastReviewDate": "2026-05-25",
      "nextRecommendedAction": "Cambiar a sustrato más aireado",
      "notes": "Evitar encharcar",
      "initialHumidifierNote": "No",
      "measurements": [
        {
          "date": "2026-05-25",
          "ph": 8.9,
          "moisture": null,
          "light": null,
          "state": "Estrés moderado",
          "note": "Medición inicial importada desde Excel"
        }
      ],
      "photos": []
    },
    {
      "id": 8,
      "slug": "philodendron-brasil-heartleaf-variegado",
      "commonName": "Philodendron Brasil / Heartleaf variegado",
      "probableSpecies": "Philodendron hederaceum variegado",
      "location": "Por definir",
      "zone": "normal",
      "plantType": "tropical_exigente",
      "humidifierPriority": "media",
      "currentPH": 6.9,
      "currentMoisture": 59,
      "currentLight": 35,
      "temperature": "Por medir",
      "generalState": "Estable",
      "diagnosis": "Luz baja; hojas amarillas por variegación/estrés",
      "mainProblem": "Luz baja; hojas amarillas por variegación/estrés",
      "urgentActions": "Mover a más luz indirecta",
      "maintenanceActions": "Podar hojas agotadas; controlar riego",
      "reviewFrequency": "Semanal",
      "lastReviewDate": "2026-05-25",
      "nextRecommendedAction": "Podar hojas agotadas; controlar riego",
      "notes": "Puede ir cerca de tropicales, no imprescindible",
      "initialHumidifierNote": "Opcional",
      "measurements": [
        {
          "date": "2026-05-25",
          "ph": 6.9,
          "moisture": 59,
          "light": 35,
          "state": "Estable",
          "note": "Medición inicial importada desde Excel"
        }
      ],
      "photos": []
    },
    {
      "id": 9,
      "slug": "dracaena-grande",
      "commonName": "Dracaena grande",
      "probableSpecies": "Dracaena fragrans",
      "location": "Por definir",
      "zone": "normal",
      "plantType": "tropical",
      "humidifierPriority": "no",
      "currentPH": 8.7,
      "currentMoisture": 9,
      "currentLight": 50,
      "temperature": "Por medir",
      "generalState": "Estresada",
      "diagnosis": "Sequía severa + pH alto",
      "mainProblem": "Sequía severa + pH alto",
      "urgentActions": "Riego profundo gradual; revisar si sustrato hidrofóbico",
      "maintenanceActions": "Trasplante a sustrato aireado",
      "reviewFrequency": "Semanal",
      "lastReviewDate": "2026-05-25",
      "nextRecommendedAction": "Trasplante a sustrato aireado",
      "notes": "No necesita humedad alta",
      "initialHumidifierNote": "No",
      "measurements": [
        {
          "date": "2026-05-25",
          "ph": 8.7,
          "moisture": 9,
          "light": 50,
          "state": "Estresada",
          "note": "Medición inicial importada desde Excel"
        }
      ],
      "photos": []
    },
    {
      "id": 10,
      "slug": "ficus-elastica-oscuro",
      "commonName": "Ficus elastica oscuro",
      "probableSpecies": "Ficus elastica Burgundy/Rubber plant",
      "location": "Por definir",
      "zone": "normal",
      "plantType": "tropical",
      "humidifierPriority": "no",
      "currentPH": 8.8,
      "currentMoisture": 5,
      "currentLight": 0,
      "temperature": "Por medir",
      "generalState": "Estrés moderado",
      "diagnosis": "Sequía severa + pH alto",
      "mainProblem": "Sequía severa + pH alto",
      "urgentActions": "Rehidratar lentamente y profundo",
      "maintenanceActions": "Trasplante próximo; agua menos alcalina",
      "reviewFrequency": "Semanal",
      "lastReviewDate": "2026-05-25",
      "nextRecommendedAction": "Trasplante próximo; agua menos alcalina",
      "notes": "Luz buena filtrada",
      "initialHumidifierNote": "No",
      "measurements": [
        {
          "date": "2026-05-25",
          "ph": 8.8,
          "moisture": 5,
          "light": 0,
          "state": "Estrés moderado",
          "note": "Medición inicial importada desde Excel"
        }
      ],
      "photos": []
    },
    {
      "id": 11,
      "slug": "dracaena-pequena",
      "commonName": "Dracaena pequeña",
      "probableSpecies": "Dracaena fragrans compacta",
      "location": "Por definir",
      "zone": "normal",
      "plantType": "tropical",
      "humidifierPriority": "no",
      "currentPH": 7,
      "currentMoisture": 5,
      "currentLight": 0,
      "temperature": "Por medir",
      "generalState": "Estrés leve",
      "diagnosis": "Sequía extrema",
      "mainProblem": "Sequía extrema",
      "urgentActions": "Riego profundo pronto",
      "maintenanceActions": "Mejorar sustrato si compactado",
      "reviewFrequency": "Semanal",
      "lastReviewDate": "2026-05-25",
      "nextRecommendedAction": "Mejorar sustrato si compactado",
      "notes": "Tolera ambiente seco",
      "initialHumidifierNote": "No",
      "measurements": [
        {
          "date": "2026-05-25",
          "ph": 7,
          "moisture": 5,
          "light": 0,
          "state": "Estrés leve",
          "note": "Medición inicial importada desde Excel"
        }
      ],
      "photos": []
    },
    {
      "id": 12,
      "slug": "pachira-aquatica-1",
      "commonName": "Pachira aquatica 1",
      "probableSpecies": "Pachira aquatica",
      "location": "Por definir",
      "zone": "normal",
      "plantType": "tropical",
      "humidifierPriority": "no",
      "currentPH": 8.4,
      "currentMoisture": 15,
      "currentLight": 0,
      "temperature": "Por medir",
      "generalState": "Estable",
      "diagnosis": "pH alto y sequía leve",
      "mainProblem": "pH alto y sequía leve",
      "urgentActions": "Riego profundo cuando toque; mejorar agua",
      "maintenanceActions": "Lavar sales ocasionalmente",
      "reviewFrequency": "Semanal",
      "lastReviewDate": "2026-05-25",
      "nextRecommendedAction": "Lavar sales ocasionalmente",
      "notes": "No humidificador prioritario",
      "initialHumidifierNote": "No",
      "measurements": [
        {
          "date": "2026-05-25",
          "ph": 8.4,
          "moisture": 15,
          "light": 0,
          "state": "Estable",
          "note": "Medición inicial importada desde Excel"
        }
      ],
      "photos": []
    },
    {
      "id": 13,
      "slug": "cactus-euphorbia-grande",
      "commonName": "Cactus/Euphorbia grande",
      "probableSpecies": "Euphorbia trigona / cactus-like",
      "location": "Por definir",
      "zone": "seca",
      "plantType": "cactus_sansevieria",
      "humidifierPriority": "no",
      "currentPH": 7.9,
      "currentMoisture": 25,
      "currentLight": 0,
      "temperature": "Por medir",
      "generalState": "Estable",
      "diagnosis": "Humedad ok; pH algo alto",
      "mainProblem": "Humedad ok; pH algo alto",
      "urgentActions": "No regar por ahora",
      "maintenanceActions": "Más luz si posible",
      "reviewFrequency": "Mensual",
      "lastReviewDate": "2026-05-25",
      "nextRecommendedAction": "Más luz si posible",
      "notes": "No humidificador",
      "initialHumidifierNote": "No",
      "measurements": [
        {
          "date": "2026-05-25",
          "ph": 7.9,
          "moisture": 25,
          "light": 0,
          "state": "Estable",
          "note": "Medición inicial importada desde Excel"
        }
      ],
      "photos": []
    },
    {
      "id": 14,
      "slug": "monstera-adansonii-grande",
      "commonName": "Monstera adansonii grande",
      "probableSpecies": "Monstera adansonii",
      "location": "Por definir",
      "zone": "normal",
      "plantType": "tropical_exigente",
      "humidifierPriority": "baja",
      "currentPH": 6.9,
      "currentMoisture": 57,
      "currentLight": 777,
      "temperature": "Por medir",
      "generalState": "Saludable",
      "diagnosis": "Leve amarilleo viejo",
      "mainProblem": "Leve amarilleo viejo",
      "urgentActions": "Mantener manejo; revisar luz",
      "maintenanceActions": "No cambios drásticos",
      "reviewFrequency": "Mensual",
      "lastReviewDate": "2026-05-25",
      "nextRecommendedAction": "No cambios drásticos",
      "notes": "pH bien",
      "initialHumidifierNote": "Opcional",
      "measurements": [
        {
          "date": "2026-05-25",
          "ph": 6.9,
          "moisture": 57,
          "light": 777,
          "state": "Saludable",
          "note": "Medición inicial importada desde Excel"
        }
      ],
      "photos": []
    },
    {
      "id": 15,
      "slug": "anthurium-longilobum-velvet",
      "commonName": "Anthurium longilobum / velvet",
      "probableSpecies": "Anthurium warocqueanum/longilobum-type",
      "location": "Por definir",
      "zone": "humidificador",
      "plantType": "tropical_exigente",
      "humidifierPriority": "alta",
      "currentPH": 7.3,
      "currentMoisture": 38,
      "currentLight": 1980,
      "temperature": "Por medir",
      "generalState": "Estrés moderado",
      "diagnosis": "Bordes secos; demanda humedad alta",
      "mainProblem": "Bordes secos; demanda humedad alta",
      "urgentActions": "Zona húmeda con humidificador",
      "maintenanceActions": "Agua menos mineralizada; no sol directo",
      "reviewFrequency": "Semanal",
      "lastReviewDate": "2026-05-25",
      "nextRecommendedAction": "Agua menos mineralizada; no sol directo",
      "notes": "Muy prioritario",
      "initialHumidifierNote": "SÍ, sí o sí",
      "measurements": [
        {
          "date": "2026-05-25",
          "ph": 7.3,
          "moisture": 38,
          "light": 1980,
          "state": "Estrés moderado",
          "note": "Medición inicial importada desde Excel"
        }
      ],
      "photos": []
    },
    {
      "id": 16,
      "slug": "peperomia-colgante",
      "commonName": "Peperomia/colgante",
      "probableSpecies": "Peperomia rotundifolia-like",
      "location": "Por definir",
      "zone": "normal",
      "plantType": "tropical",
      "humidifierPriority": "no",
      "currentPH": 7.9,
      "currentMoisture": 27,
      "currentLight": 862,
      "temperature": "Por medir",
      "generalState": "Estrés alto",
      "diagnosis": "Tallos secos, poca densidad",
      "mainProblem": "Tallos secos, poca densidad",
      "urgentActions": "Podar y propagar",
      "maintenanceActions": "Más luz, mezcla drenante",
      "reviewFrequency": "Semanal",
      "lastReviewDate": "2026-05-25",
      "nextRecommendedAction": "Más luz, mezcla drenante",
      "notes": "No humidificador",
      "initialHumidifierNote": "No",
      "measurements": [
        {
          "date": "2026-05-25",
          "ph": 7.9,
          "moisture": 27,
          "light": 862,
          "state": "Estrés alto",
          "note": "Medición inicial importada desde Excel"
        }
      ],
      "photos": []
    },
    {
      "id": 17,
      "slug": "alocasia-silver-dragon-like",
      "commonName": "Alocasia Silver Dragon-like",
      "probableSpecies": "Alocasia baginda-type",
      "location": "Por definir",
      "zone": "humidificador",
      "plantType": "tropical_exigente",
      "humidifierPriority": "alta",
      "currentPH": 6.7,
      "currentMoisture": 73,
      "currentLight": 1165,
      "temperature": "Por medir",
      "generalState": "Estrés alto",
      "diagnosis": "Sustrato húmedo pero bordes secos",
      "mainProblem": "Sustrato húmedo pero bordes secos",
      "urgentActions": "Poner en zona húmeda; no regar hasta bajar",
      "maintenanceActions": "Revisar raíces si empeora",
      "reviewFrequency": "Semanal",
      "lastReviewDate": "2026-05-25",
      "nextRecommendedAction": "Revisar raíces si empeora",
      "notes": "Humedad ambiental alta, aireación",
      "initialHumidifierNote": "SÍ, sí o sí",
      "measurements": [
        {
          "date": "2026-05-25",
          "ph": 6.7,
          "moisture": 73,
          "light": 1165,
          "state": "Estrés alto",
          "note": "Medición inicial importada desde Excel"
        }
      ],
      "photos": []
    },
    {
      "id": 18,
      "slug": "philodendron-melanochrysum",
      "commonName": "Philodendron melanochrysum",
      "probableSpecies": "Philodendron melanochrysum",
      "location": "Por definir",
      "zone": "humidificador",
      "plantType": "tropical_exigente",
      "humidifierPriority": "alta",
      "currentPH": 7.3,
      "currentMoisture": 38,
      "currentLight": 3480,
      "temperature": "Por medir",
      "generalState": "Bueno/estable",
      "diagnosis": "Tutor de musgo seco; hojas pequeñas/daños leves",
      "mainProblem": "Tutor de musgo seco; hojas pequeñas/daños leves",
      "urgentActions": "Humidificador + humedecer tutor",
      "maintenanceActions": "Mantener sustrato chunky",
      "reviewFrequency": "Semanal",
      "lastReviewDate": "2026-05-25",
      "nextRecommendedAction": "Mantener sustrato chunky",
      "notes": "No empapar maceta",
      "initialHumidifierNote": "SÍ, muy recomendable",
      "measurements": [
        {
          "date": "2026-05-25",
          "ph": 7.3,
          "moisture": 38,
          "light": 3480,
          "state": "Bueno/estable",
          "note": "Medición inicial importada desde Excel"
        }
      ],
      "photos": []
    },
    {
      "id": 19,
      "slug": "ficus-lyrata",
      "commonName": "Ficus lyrata",
      "probableSpecies": "Ficus lyrata",
      "location": "Por definir",
      "zone": "normal",
      "plantType": "tropical",
      "humidifierPriority": "no",
      "currentPH": 5.8,
      "currentMoisture": 95,
      "currentLight": 5200,
      "temperature": "Por medir",
      "generalState": "Estrés moderado",
      "diagnosis": "Exceso severo de humedad",
      "mainProblem": "Exceso severo de humedad",
      "urgentActions": "Suspender riego; airear sustrato",
      "maintenanceActions": "Trasplante a mezcla aireada",
      "reviewFrequency": "Semanal",
      "lastReviewDate": "2026-05-25",
      "nextRecommendedAction": "Trasplante a mezcla aireada",
      "notes": "pH perfecto",
      "initialHumidifierNote": "No",
      "measurements": [
        {
          "date": "2026-05-25",
          "ph": 5.8,
          "moisture": 95,
          "light": 5200,
          "state": "Estrés moderado",
          "note": "Medición inicial importada desde Excel"
        }
      ],
      "photos": []
    },
    {
      "id": 20,
      "slug": "alocasia-frydek-amazonica",
      "commonName": "Alocasia Frydek/amazonica",
      "probableSpecies": "Alocasia micholitziana Frydek / amazonica",
      "location": "Por definir",
      "zone": "humidificador",
      "plantType": "tropical_exigente",
      "humidifierPriority": "alta",
      "currentPH": 8,
      "currentMoisture": 23,
      "currentLight": 0,
      "temperature": "Por medir",
      "generalState": "Saludable con estrés",
      "diagnosis": "pH alto + sustrato seco",
      "mainProblem": "pH alto + sustrato seco",
      "urgentActions": "Riego profundo y poner en zona húmeda",
      "maintenanceActions": "Agua menos alcalina; luz indirecta brillante",
      "reviewFrequency": "Semanal",
      "lastReviewDate": "2026-05-25",
      "nextRecommendedAction": "Agua menos alcalina; luz indirecta brillante",
      "notes": "La alocasia confirmada por foto",
      "initialHumidifierNote": "SÍ, sí o sí",
      "measurements": [
        {
          "date": "2026-05-25",
          "ph": 8,
          "moisture": 23,
          "light": 0,
          "state": "Saludable con estrés",
          "note": "Medición inicial importada desde Excel"
        }
      ],
      "photos": []
    },
    {
      "id": 21,
      "slug": "philodendron-rojo-oscuro",
      "commonName": "Philodendron rojo oscuro",
      "probableSpecies": "Philodendron erubescens hybrid",
      "location": "Por definir",
      "zone": "normal",
      "plantType": "tropical_exigente",
      "humidifierPriority": "media",
      "currentPH": 7,
      "currentMoisture": 5,
      "currentLight": 1430,
      "temperature": "Por medir",
      "generalState": "Estable pero seca",
      "diagnosis": "Sequía extrema; posible rootbound",
      "mainProblem": "Sequía extrema; posible rootbound",
      "urgentActions": "Riego profundo y vaciar contenedor externo",
      "maintenanceActions": "Trasplante a mezcla aireada",
      "reviewFrequency": "Semanal",
      "lastReviewDate": "2026-05-25",
      "nextRecommendedAction": "Trasplante a mezcla aireada",
      "notes": "No tan exigente como anthurium/alocasia",
      "initialHumidifierNote": "Opcional alto",
      "measurements": [
        {
          "date": "2026-05-25",
          "ph": 7,
          "moisture": 5,
          "light": 1430,
          "state": "Estable pero seca",
          "note": "Medición inicial importada desde Excel"
        }
      ],
      "photos": []
    },
    {
      "id": 22,
      "slug": "monstera-thai-constellation",
      "commonName": "Monstera Thai Constellation",
      "probableSpecies": "Monstera deliciosa Thai Constellation",
      "location": "Por definir",
      "zone": "normal",
      "plantType": "tropical_exigente",
      "humidifierPriority": "media",
      "currentPH": 6.9,
      "currentMoisture": 49,
      "currentLight": 22,
      "temperature": "Por medir",
      "generalState": "Saludable",
      "diagnosis": "Leves daños mecánicos; requiere buena luz",
      "mainProblem": "Leves daños mecánicos; requiere buena luz",
      "urgentActions": "Mantener riego; evitar agua estancada",
      "maintenanceActions": "Más luz indirecta; fertilización suave",
      "reviewFrequency": "Semanal",
      "lastReviewDate": "2026-05-25",
      "nextRecommendedAction": "Más luz indirecta; fertilización suave",
      "notes": "No imprescindible",
      "initialHumidifierNote": "Opcional",
      "measurements": [
        {
          "date": "2026-05-25",
          "ph": 6.9,
          "moisture": 49,
          "light": 22,
          "state": "Saludable",
          "note": "Medición inicial importada desde Excel"
        }
      ],
      "photos": []
    },
    {
      "id": 23,
      "slug": "ficus-elastica-tineke",
      "commonName": "Ficus elastica Tineke",
      "probableSpecies": "Ficus elastica Tineke",
      "location": "Por definir",
      "zone": "normal",
      "plantType": "tropical",
      "humidifierPriority": "no",
      "currentPH": 8.8,
      "currentMoisture": 5,
      "currentLight": 0,
      "temperature": "Por medir",
      "generalState": "Estrés moderado",
      "diagnosis": "Sequía severa + pH muy alto",
      "mainProblem": "Sequía severa + pH muy alto",
      "urgentActions": "Rehidratación profunda lenta",
      "maintenanceActions": "Trasplante a mezcla aireada; agua menos alcalina",
      "reviewFrequency": "Semanal",
      "lastReviewDate": "2026-05-25",
      "nextRecommendedAction": "Trasplante a mezcla aireada; agua menos alcalina",
      "notes": "No humidificador",
      "initialHumidifierNote": "No",
      "measurements": [
        {
          "date": "2026-05-25",
          "ph": 8.8,
          "moisture": 5,
          "light": 0,
          "state": "Estrés moderado",
          "note": "Medición inicial importada desde Excel"
        }
      ],
      "photos": []
    },
    {
      "id": 24,
      "slug": "dracaena-fragrans-grande-triste",
      "commonName": "Dracaena fragrans grande triste",
      "probableSpecies": "Dracaena fragrans",
      "location": "Por definir",
      "zone": "normal",
      "plantType": "tropical",
      "humidifierPriority": "no",
      "currentPH": 6.9,
      "currentMoisture": 51,
      "currentLight": 730,
      "temperature": "Por medir",
      "generalState": "Muy estresada",
      "diagnosis": "Probable daño radicular/matera muy grande",
      "mainProblem": "Probable daño radicular/matera muy grande",
      "urgentActions": "Revisar raíces YA",
      "maintenanceActions": "Reducir matera y sustrato aireado",
      "reviewFrequency": "Mensual",
      "lastReviewDate": "2026-05-25",
      "nextRecommendedAction": "Reducir matera y sustrato aireado",
      "notes": "Humedad ambiental no resuelve el problema",
      "initialHumidifierNote": "No",
      "measurements": [
        {
          "date": "2026-05-25",
          "ph": 6.9,
          "moisture": 51,
          "light": 730,
          "state": "Muy estresada",
          "note": "Medición inicial importada desde Excel"
        }
      ],
      "photos": []
    },
    {
      "id": 25,
      "slug": "dracaena-compacta",
      "commonName": "Dracaena compacta",
      "probableSpecies": "Dracaena fragrans compacta",
      "location": "Por definir",
      "zone": "normal",
      "plantType": "tropical",
      "humidifierPriority": "no",
      "currentPH": 7.4,
      "currentMoisture": 36,
      "currentLight": 227,
      "temperature": "Por medir",
      "generalState": "Saludable",
      "diagnosis": "Luz baja; sustrato compacto",
      "mainProblem": "Luz baja; sustrato compacto",
      "urgentActions": "Regar pronto si baja más",
      "maintenanceActions": "Aumentar luz indirecta",
      "reviewFrequency": "Mensual",
      "lastReviewDate": "2026-05-25",
      "nextRecommendedAction": "Aumentar luz indirecta",
      "notes": "No humidificador",
      "initialHumidifierNote": "No",
      "measurements": [
        {
          "date": "2026-05-25",
          "ph": 7.4,
          "moisture": 36,
          "light": 227,
          "state": "Saludable",
          "note": "Medición inicial importada desde Excel"
        }
      ],
      "photos": []
    },
    {
      "id": 26,
      "slug": "sansevieria-1",
      "commonName": "Sansevieria 1",
      "probableSpecies": "Sansevieria trifasciata",
      "location": "Por definir",
      "zone": "seca",
      "plantType": "cactus_sansevieria",
      "humidifierPriority": "no",
      "currentPH": 7.9,
      "currentMoisture": 26,
      "currentLight": 0,
      "temperature": "Por medir",
      "generalState": "Saludable",
      "diagnosis": "pH alto pero tolerado",
      "mainProblem": "pH alto pero tolerado",
      "urgentActions": "No regar todavía",
      "maintenanceActions": "Más drenaje en próximo trasplante",
      "reviewFrequency": "Mensual",
      "lastReviewDate": "2026-05-25",
      "nextRecommendedAction": "Más drenaje en próximo trasplante",
      "notes": "Prefiere seco",
      "initialHumidifierNote": "No",
      "measurements": [
        {
          "date": "2026-05-25",
          "ph": 7.9,
          "moisture": 26,
          "light": 0,
          "state": "Saludable",
          "note": "Medición inicial importada desde Excel"
        }
      ],
      "photos": []
    },
    {
      "id": 27,
      "slug": "sansevieria-2",
      "commonName": "Sansevieria 2",
      "probableSpecies": "Sansevieria trifasciata",
      "location": "Por definir",
      "zone": "seca",
      "plantType": "cactus_sansevieria",
      "humidifierPriority": "no",
      "currentPH": 7.4,
      "currentMoisture": 37,
      "currentLight": 0,
      "temperature": "Por medir",
      "generalState": "Excelente",
      "diagnosis": "Leve alcalinidad",
      "mainProblem": "Leve alcalinidad",
      "urgentActions": "No regar aún",
      "maintenanceActions": "Mantener ubicación",
      "reviewFrequency": "Mensual",
      "lastReviewDate": "2026-05-25",
      "nextRecommendedAction": "Mantener ubicación",
      "notes": "Prefiere seco",
      "initialHumidifierNote": "No",
      "measurements": [
        {
          "date": "2026-05-25",
          "ph": 7.4,
          "moisture": 37,
          "light": 0,
          "state": "Excelente",
          "note": "Medición inicial importada desde Excel"
        }
      ],
      "photos": []
    },
    {
      "id": 28,
      "slug": "fairy-castle-cactus",
      "commonName": "Fairy Castle cactus",
      "probableSpecies": "Cereus tetragonus-like",
      "location": "Por definir",
      "zone": "seca",
      "plantType": "cactus_sansevieria",
      "humidifierPriority": "no",
      "currentPH": 7,
      "currentMoisture": 5,
      "currentLight": 0,
      "temperature": "Por medir",
      "generalState": "Bueno",
      "diagnosis": "Poca luz relativa",
      "mainProblem": "Poca luz relativa",
      "urgentActions": "Mover a más luz",
      "maintenanceActions": "Riego profundo solo cuando toque",
      "reviewFrequency": "Mensual",
      "lastReviewDate": "2026-05-25",
      "nextRecommendedAction": "Riego profundo solo cuando toque",
      "notes": "No humidificador",
      "initialHumidifierNote": "No",
      "measurements": [
        {
          "date": "2026-05-25",
          "ph": 7,
          "moisture": 5,
          "light": 0,
          "state": "Bueno",
          "note": "Medición inicial importada desde Excel"
        }
      ],
      "photos": []
    },
    {
      "id": 29,
      "slug": "calathea-stromanthe-roja",
      "commonName": "Calathea/Stromanthe roja",
      "probableSpecies": "Calathea/Stromanthe/Marantaceae",
      "location": "Por definir",
      "zone": "humidificador",
      "plantType": "tropical_exigente",
      "humidifierPriority": "alta",
      "currentPH": 7.6,
      "currentMoisture": 33,
      "currentLight": 0,
      "temperature": "Por medir",
      "generalState": "Estresada",
      "diagnosis": "Hojas caídas, bordes secos, poca luz",
      "mainProblem": "Hojas caídas, bordes secos, poca luz",
      "urgentActions": "Mover a luz indirecta y humidificador",
      "maintenanceActions": "Agua filtrada; revisar raíces",
      "reviewFrequency": "Semanal",
      "lastReviewDate": "2026-05-25",
      "nextRecommendedAction": "Agua filtrada; revisar raíces",
      "notes": "Muy sensible a humedad y agua dura",
      "initialHumidifierNote": "SÍ, sí o sí",
      "measurements": [
        {
          "date": "2026-05-25",
          "ph": 7.6,
          "moisture": 33,
          "light": 0,
          "state": "Estresada",
          "note": "Medición inicial importada desde Excel"
        }
      ],
      "photos": []
    }
  ],
  "activityLog": [],
  "completedTasks": []
}